pyTecanFluent
tests
