Metadata-Version: 1.1
Name: pyTecanFluent
Version: 0.1.0
Summary: Python interface to TECAN Fluent liquid handling robot
Home-page: https://github.com/leylabmpi/pyTecanFluent
Author: Nick Youngblut
Author-email: leylabmpi@gmail.com
License: MIT license
Keywords: pyTecanFluent
Platform: UNKNOWN
Classifier: Programming Language :: Python :: 2
Classifier: Programming Language :: Python :: 2.7
Classifier: Programming Language :: Python :: 3
Classifier: Programming Language :: Python :: 3.3
Classifier: Programming Language :: Python :: 3.4
Classifier: Programming Language :: Python :: 3.5
